MANIFEST.in
README.md
setup.cfg
setup.py
versioneer.py
csirtg_urlsml/__init__.py
csirtg_urlsml/_version.py
csirtg_urlsml/constants.py
csirtg_urlsml/train.py
csirtg_urlsml/url.py
csirtg_urlsml.egg-info/PKG-INFO
csirtg_urlsml.egg-info/SOURCES.txt
csirtg_urlsml.egg-info/dependency_links.txt
csirtg_urlsml.egg-info/entry_points.txt
csirtg_urlsml.egg-info/requires.txt
csirtg_urlsml.egg-info/top_level.txt
data/blacklist.txt
data/model.pickle
data/model_py2.pickle
data/whitelist.txt
test/__init__.py
test/test_basics.py