Metadata-Version: 1.0
Name: csirtg-urlsml
Version: 0.0.0a2
Summary: CSIRTG URLs ML Framework
Home-page: https://github.com/csirtgadgets/csirtg-urlsml-py
Author: Wes Young
Author-email: wes@barely3am.com
License: MPLv2
Keywords: network,security
Platform: UNKNOWN
